README.rst
setup.py
gstack/__init__.py
gstack/__main__.py
gstack/authentication.py
gstack/configure.py
gstack/core.py
gstack/helpers.py
gstack/oauth2provider.py
gstack.egg-info/PKG-INFO
gstack.egg-info/SOURCES.txt
gstack.egg-info/dependency_links.txt
gstack.egg-info/entry_points.txt
gstack.egg-info/not-zip-safe
gstack.egg-info/requires.txt
gstack.egg-info/top_level.txt
gstack/controllers/OAuth2.py
gstack/controllers/__init__.py
gstack/controllers/disks.py
gstack/controllers/errors.py
gstack/controllers/firewalls.py
gstack/controllers/images.py
gstack/controllers/index.py
gstack/controllers/instances.py
gstack/controllers/machine_type.py
gstack/controllers/networks.py
gstack/controllers/operations.py
gstack/controllers/project.py
gstack/controllers/regions.py
gstack/controllers/zones.py
gstack/data/server.crt
gstack/data/server.key
gstack/models/__init__.py
gstack/models/accesstoken.py
gstack/models/client.py
gstack/models/refreshtoken.py
gstack/services/__init__.py
gstack/services/requester.py
migrations/env.py
pyoauth2/__init__.py
pyoauth2/client.py
pyoauth2/provider.py
pyoauth2/utils.py