Metadata-Version: 1.1
Name: gstack
Version: 1.1.1
Summary: A GCE interface to Apache CloudStack
Home-page: https://github.com/NOPping/gstack
Author: Ian Duffy, Darren Brogan, Sebastien Goasguen
Author-email: ian@ianduffy.ie, brogand93@darrenbrogan.ie, runseb@gmail.com
License: LICENSE.txt
Platform: Any
Classifier: Development Status :: 3 - Alpha
Classifier: Environment :: Console
Classifier: Intended Audience :: System Administrators
Classifier: License :: OSI Approved :: Apache Software License
Classifier: Operating System :: OS Independent
Classifier: Programming Language :: Python
Classifier: Topic :: Utilities
Classifier: Programming Language :: Python :: 2.7
